audinterface/__init__.py
audinterface/conftest.py
audinterface/core/__init__.py
audinterface/core/feature.py
audinterface/core/process.py
audinterface/core/process_with_context.py
audinterface/core/segment.py
audinterface/core/segment_with_feature.py
audinterface/core/typing.py
audinterface/core/utils.py
audinterface/utils/__init__.py
audinterface-1.3.0.dist-info/licenses/LICENSE
docs/changelog.rst
docs/conf.py
docs/conftest.py
docs/contributing.rst
docs/genindex.rst
docs/index.rst
docs/installation.rst
docs/usage.rst
docs/api-src/audinterface.rst
docs/api-src/audinterface.utils.rst
misc/logo.png
tests/conftest.py
tests/test_feature.py
tests/test_process.py
tests/test_process_func_args.py
tests/test_process_with_context.py
tests/test_segment.py
tests/test_segment_with_feature.py
tests/test_utils.py
audinterface-1.3.0.dist-info/METADATA
audinterface-1.3.0.dist-info/WHEEL
audinterface-1.3.0.dist-info/top_level.txt
audinterface-1.3.0.dist-info/RECORD
