Metadata-Version: 2.4
Name: audinterface
Version: 1.3.0
Summary: Generic interfaces for signal processing
Author: Johannes Wagner, Andreas Triantafyllopoulos
Author-email: Hagen Wierstorf <hwierstorf@audeering.com>, Maximilian Schmitt <mschmitt@audeering.com>
License: MIT License
Project-URL: repository, https://github.com/audeering/audinterface/
Project-URL: documentation, https://audeering.github.io/audinterface/
Keywords: audio,dsp,machine learning
Classifier: Development Status :: 5 - Production/Stable
Classifier: Intended Audience :: Science/Research
Classifier: Intended Audience :: Developers
Classifier: License :: OSI Approved :: MIT License
Classifier: Operating System :: OS Independent
Classifier: Programming Language :: Python
Classifier: Programming Language :: Python :: 3
Classifier: Programming Language :: Python :: 3.9
Classifier: Programming Language :: Python :: 3.10
Classifier: Programming Language :: Python :: 3.11
Classifier: Programming Language :: Python :: 3.12
Classifier: Programming Language :: Python :: 3.13
Classifier: Topic :: Scientific/Engineering
Requires-Python: >=3.9
License-File: LICENSE
Requires-Dist: audeer>=2.1.1
Requires-Dist: audformat<2.0.0,>=1.0.1
Requires-Dist: audiofile>=1.3.0
Requires-Dist: audmath>=1.4.1
Requires-Dist: audresample<2.0.0,>=1.1.0
Dynamic: license-file
